pymacaroons/__init__.py
pymacaroons/caveat.py
pymacaroons/exceptions.py
pymacaroons/macaroon.py
pymacaroons/utils.py
pymacaroons/verifier.py
pymacaroons/binders/__init__.py
pymacaroons/binders/base_binder.py
pymacaroons/binders/hash_signatures_binder.py
pymacaroons/caveat_delegates/__init__.py
pymacaroons/caveat_delegates/base_first_party.py
pymacaroons/caveat_delegates/base_third_party.py
pymacaroons/caveat_delegates/encrypted_first_party.py
pymacaroons/caveat_delegates/first_party.py
pymacaroons/caveat_delegates/third_party.py
pymacaroons/field_encryptors/__init__.py
pymacaroons/field_encryptors/base_field_encryptor.py
pymacaroons/field_encryptors/secret_box_encryptor.py
pymacaroons/serializers/__init__.py
pymacaroons/serializers/base_serializer.py
pymacaroons/serializers/binary_serializer.py
pymacaroons/serializers/json_serializer.py
pymacaroons-0.12.0.dist-info/DESCRIPTION.rst
pymacaroons-0.12.0.dist-info/METADATA
pymacaroons-0.12.0.dist-info/RECORD
pymacaroons-0.12.0.dist-info/WHEEL
pymacaroons-0.12.0.dist-info/metadata.json
pymacaroons-0.12.0.dist-info/top_level.txt
